stopforumspam/__init__.py
stopforumspam/admin.py
stopforumspam/compat.py
stopforumspam/middleware.py
stopforumspam/models.py
stopforumspam/settings.py
stopforumspam/tests.py
stopforumspam/views.py
stopforumspam/management/__init__.py
stopforumspam/management/commands/__init__.py
stopforumspam/management/commands/sfsupdate.py
stopforumspam/migrations/0001_initial.py
stopforumspam/migrations/__init__.py
stopforumspam/templates/stopforumspam/denied.html
stopforumspam-1.11.dist-info/METADATA
stopforumspam-1.11.dist-info/WHEEL
stopforumspam-1.11.dist-info/pbr.json
stopforumspam-1.11.dist-info/top_level.txt
stopforumspam-1.11.dist-info/RECORD
