Metadata-Version: 2.1
Name: stopforumspam
Version: 1.11
Summary: Django middleware for blocking IPs listed in stopforumspam.com
Home-page: https://overtag.dk/
Author: Benjamin Bach
Author-email: benjamin@overtag.dk
License: BSD License
Platform: UNKNOWN
Classifier: Development Status :: 4 - Beta
Classifier: Environment :: Web Environment
Classifier: Framework :: Django
Classifier: Intended Audience :: Developers
Classifier: License :: OSI Approved :: BSD License
Classifier: Operating System :: OS Independent
Classifier: Programming Language :: Python
Classifier: Topic :: Internet :: WWW/HTTP :: Dynamic Content
Classifier: Topic :: Software Development
Classifier: Topic :: Software Development :: Libraries :: Application Frameworks
Requires-Dist: Django (>=1.9)
